compare_date_range/__init__.py
compare_date_range/main.py
tests/__init__.py
compare_date_range-0.0.1.dist-info/LICENSE
compare_date_range-0.0.1.dist-info/METADATA
compare_date_range-0.0.1.dist-info/WHEEL
compare_date_range-0.0.1.dist-info/top_level.txt
compare_date_range-0.0.1.dist-info/RECORD
